enzyme/__init__.py
enzyme/exceptions.py
enzyme/mkv.py
enzyme/parsers/__init__.py
enzyme/parsers/ebml/__init__.py
enzyme/parsers/ebml/core.py
enzyme/parsers/ebml/readers.py
enzyme/parsers/ebml/specs/matroska.xml
enzyme-0.5.2.dist-info/LICENSE
enzyme-0.5.2.dist-info/METADATA
enzyme-0.5.2.dist-info/WHEEL
enzyme-0.5.2.dist-info/top_level.txt
enzyme-0.5.2.dist-info/RECORD
